mongoflex/__init__.py
mongoflex/connection.py
mongoflex/models.py
mongoflex-0.3.0.dist-info/LICENSE
mongoflex-0.3.0.dist-info/METADATA
mongoflex-0.3.0.dist-info/WHEEL
mongoflex-0.3.0.dist-info/RECORD
