Metadata-Version: 2.1
Name: mongoflex
Version: 0.3.0
Summary: Mongoflex is a ORM-like wrapper for mongodb to allow declarative creation and management of mongo collections.
License: MIT
Author: Giancarlo Rocha
Author-email: giancarloiff@gmail.com
Requires-Python: >=3.8,<4.0
Classifier: License :: OSI Approved :: MIT License
Classifier: Programming Language :: Python :: 3
Classifier: Programming Language :: Python :: 3.8
Classifier: Programming Language :: Python :: 3.9
Classifier: Programming Language :: Python :: 3.10
Classifier: Programming Language :: Python :: 3.11
Classifier: Programming Language :: Python :: 3.12
Requires-Dist: inflect (>=7.0.0,<8.0.0)
Requires-Dist: pymongo (>=4.4.1,<5.0.0)
